integration_tests/__init__.py
integration_tests/test_primero_api.py
primero_api/__init__.py
primero_api/logger.py
primero_api/primero_api.py
primero_api/report.py
primero_api/report_processors.py
primero_api/version.py
tests/__init__.py
tests/test_primero_api.py
primero_api-0.2.4.dist-info/METADATA
primero_api-0.2.4.dist-info/WHEEL
primero_api-0.2.4.dist-info/top_level.txt
primero_api-0.2.4.dist-info/RECORD
