Metadata-Version: 2.1
Name: primero-api
Version: 0.2.4
Summary: A simple client for consuming data from Primero API
Home-page: https://github.com/unicef/magasin-primero-paquet
Author: merlos
Author-email: merlos@users.github.com
Classifier: Programming Language :: Python :: 3
Classifier: License :: OSI Approved :: MIT License
Classifier: Operating System :: OS Independent
Requires-Python: >=3.6
Requires-Dist: requests
Requires-Dist: requests-cache
Requires-Dist: requests-ratelimiter
Requires-Dist: pandas
Requires-Dist: pyarrow
Requires-Dist: python-slugify
Provides-Extra: dev
Requires-Dist: pytest ; extra == 'dev'
Requires-Dist: pytest-cov ; extra == 'dev'
Requires-Dist: pytest-mock ; extra == 'dev'
Requires-Dist: flake8 ; extra == 'dev'
Requires-Dist: black ; extra == 'dev'
Requires-Dist: isort ; extra == 'dev'
Requires-Dist: mypy ; extra == 'dev'
Requires-Dist: sphinx ; extra == 'dev'
Requires-Dist: sphinx-rtd-theme ; extra == 'dev'
Requires-Dist: requests-mock ; extra == 'dev'
